g4x_helpers/__init__.py
g4x_helpers/cli/cli.py
g4x_helpers/cli/cli_setup.py
g4x_helpers/cli/help_messages.py
g4x_helpers/g4x_viewer/CellMasksSchema.proto
g4x_helpers/g4x_viewer/CellMasksSchema_pb2.py
g4x_helpers/g4x_viewer/CellMasksSchema_pb2.pyi
g4x_helpers/g4x_viewer/TranscriptsSchema.proto
g4x_helpers/g4x_viewer/TranscriptsSchema_pb2.py
g4x_helpers/g4x_viewer/TranscriptsSchema_pb2.pyi
g4x_helpers/main_features.py
g4x_helpers/models.py
g4x_helpers/modules/__init__.py
g4x_helpers/modules/demux.py
g4x_helpers/modules/edit_bin.py
g4x_helpers/modules/init_bin.py
g4x_helpers/modules/segment.py
g4x_helpers/modules/transcript_tar.py
g4x_helpers/modules/viewer_dir.py
g4x_helpers/modules/workflow.py
g4x_helpers/schemas/base_schema.txt
g4x_helpers/schemas/migration.py
g4x_helpers/schemas/validate.py
g4x_helpers/utils.py
g4x_helpers-2.1.2.dist-info/WHEEL
g4x_helpers-2.1.2.dist-info/entry_points.txt
g4x_helpers-2.1.2.dist-info/METADATA
g4x_helpers-2.1.2.dist-info/RECORD
