Metadata-Version: 2.3
Name: g4x_helpers
Version: 2.1.2
Summary: Python helpers for G4X.
Author: Kenneth Gouin III, Florian Raths
Author-email: Kenneth Gouin III <kennethg@singulargenomics.com>, Florian Raths <flo.raths@singulargenomics.com>
License: MIT
Classifier: Development Status :: 4 - Beta
Classifier: Intended Audience :: Developers
Classifier: License :: OSI Approved :: MIT License
Classifier: Programming Language :: Python :: 3
Classifier: Programming Language :: Python :: 3.12
Classifier: Topic :: Scientific/Engineering :: Bio-Informatics
Requires-Dist: geopandas~=1.0
Requires-Dist: glymur~=0.12,<=0.13.4
Requires-Dist: matplotlib~=3.7
Requires-Dist: polars~=1.30
Requires-Dist: protobuf~=4.25
Requires-Dist: rasterio~=1.4
Requires-Dist: scanpy~=1.10
Requires-Dist: scikit-image~=0.25
Requires-Dist: shapely~=2.1
Requires-Dist: pyarrow~=16.1
Requires-Dist: rich-click~=1.9
Requires-Dist: pathschema~=0.2.1
Requires-Python: >=3.10, <3.13
Project-URL: repository, https://github.com/Singular-Genomics/G4X-helpers
